[
  {
    "ContainingType": "BoxesTecnom.Controllers.AppointmentsController",
    "Method": "GetAppointments",
    "RelativePath": "api/appointments",
    "HttpMethod": "GET",
    "IsController": true,
    "Order": 0,
    "Parameters": [],
    "ReturnTypes": [
      {
        "Type": "System.Collections.Generic.IEnumerable\u00601[[BoxesTecnom.Models.Appointment, BoxesTecnom, Version=1.0.0.0, Culture=neutral, PublicKeyToken=null]]",
        "MediaTypes": [
          "text/plain",
          "application/json",
          "text/json"
        ],
        "StatusCode": 200
      }
    ]
  },
  {
    "ContainingType": "BoxesTecnom.Controllers.AppointmentsController",
    "Method": "AddAppointment",
    "RelativePath": "api/appointments",
    "HttpMethod": "POST",
    "IsController": true,
    "Order": 0,
    "Parameters": [
      {
        "Name": "appointmentDto",
        "Type": "BoxesTecnom.Dtos.AppointmentRequestDto",
        "IsRequired": true
      }
    ],
    "ReturnTypes": []
  },
  {
    "ContainingType": "BoxesTecnom.Controllers.WorkshopsController",
    "Method": "GetWorkshops",
    "RelativePath": "api/workshops",
    "HttpMethod": "GET",
    "IsController": true,
    "Order": 0,
    "Parameters": [],
    "ReturnTypes": [
      {
        "Type": "System.Collections.Generic.IEnumerable\u00601[[BoxesTecnom.Models.Workshop, BoxesTecnom, Version=1.0.0.0, Culture=neutral, PublicKeyToken=null]]",
        "MediaTypes": [
          "text/plain",
          "application/json",
          "text/json"
        ],
        "StatusCode": 200
      }
    ]
  }
]